{"cameraMode":{"drawMode":0,"name":"Shaded","section":"Shading Mode"},"sceneLighting":true,"audioPlay":false,"sceneViewState":{"m_AlwaysRefresh":false,"showFog":true,"showSkybox":true,"showFlares":true,"showImageEffects":true,"showParticleSystems":true,"showVisualEffectGraphs":true,"m_FxEnabled":true},"in2DMode":false,"pivot":{"x":-9.601425170898438,"y":3.6717801094055177,"z":32.29852294921875},"rotation":{"x":-0.13536125421524049,"y":0.4999200999736786,"z":-0.07930252701044083,"w":-0.8519062399864197},"size":4.165607929229736,"orthographic":false}